[{"c":357,"align":79,"start":79,"posit":79,"не":20,"да":18,"эт":17,"и":17,"что":16,"ты":15,"я":13,"но":10,"неплох":9,"а":8,"дума":8,"в":8,"лучш":7,"все":7,"так":7,"защит":7,"быт":6,"на":5,"ещ":5,"мне":5,"до":5,"ну":5,"игра":5,"скорост":5,"дриблинг":5,"нрав":5,"то":5,"виде":4,"мног":4,"фиф":4,"спасиб":4,"мы":4,"рейтинг":4,"он":4,"дава":4,"брата":4,"должн":4,"довол":4,"как":4,"прост":4,"кажет":4,"сам":4,"вот":4,"nbsp":4,"подписа":3,"сказа":3,"нов":3,"ребят":3,"над":3,"ладн":3,"удар":3,"был":3,"фотк":3,"наш":3,"для":3,"же":3,"вообщ":3,"уж":3,"физ":3,"подготовк":3,"конечн":3,"теб":3,"заслужива":3,"кана":2,"кто":2,"очен":2,"ролик":2,"реакц":2,"футболист":2,"за":2,"всем":2,"зна":2,"тож":2,"гот":2,"посмотр":2,"там":2,"номер":2,"у":2,"мен":2,"соглас":2,"пас":2,"хуж":2,"цел":2,"тогд":2,"неуважен":2,"мо":2,"нормальн":2,"даж":2,"могл":2,"из":2,"быстр":2,"хорош":2,"наслажда":2,"ест":2,"немн":2,"игр":2,"выш":2,"недовольн":2,"пойд":2,"нужн":2,"готов":2,"всегд":2,"чтож":2,"име":2,"чтоб":2,"след":2,"год":2,"вы":2,"webvtt":1,"kind":1,"caption":1,"languag":1,"ru":1,"друз":1,"перед":1,"начал":1,"прош":1,"всех":1,"тех":1,"вперед":1,"посвящен":1,"способ":1,"канал":1,"перевод":1,"озвучк":1,"нажа":1,"кнопк":1,"откликнул":1,"сейчас":1,"переход":1,"к":1,"жела":1,"приятн":1,"просмотр":1,"здоров":1,"ждал":1,"момент":1,"вышл":1,"тепер":1,"сегодн":1,"увид":1,"узна":1,"повесел":1,"блин":1,"ноч":1,"погна":1,"потиш":1,"youtub":1,"снача":1,"нич":1,"смотрет":1,"десят":1,"персональн":1,"карточк":1,"ч":1,"больш":1,"маловат":1,"защища":1,"намн":1,"паз":1,"норм":1,"хочеш":1,"забива":1,"азар":1,"два":1,"когд":1,"нибуд":1,"стан":1,"перв":1,"будет":1,"сложн":1,"джуд":1,"биллинг":1,"нет":1,"тво":1,"чем":1,"поч":1,"отвеча":1,"глян":1,"chuse":1,"спасл":1,"скольк":1,"врод":1,"показател":1,"выгляд":1,"прекраща":1,"выгляж":1,"жизн":1,"ужасн":1,"передач":1,"бож":1,"худш":1,"написа":1,"чувств":1,"будт":1,"смотр":1,"матч":1,"зат":1,"вид":1,"дел":1,"порядк":1,"защитник":1,"один":1,"шкипер":1,"капита":1,"классн":1,"плох":1,"жест":1,"долж":1,"ва":1,"мнен":1,"ем":1,"есл":1,"капитан":1,"нам":1,"наслад":1,"никак":1,"физподготовк":1,"постоя":1,"зал":1,"иногд":1,"туд":1,"захож":1,"запека":1,"добр":1,"пожалова":1,"че":1,"хрен":1,"ид":1,"сюд":1,"but":1,"поговор":1,"насчет":1,"хоч":1,"пап":1,"левандовск":1,"без":1,"комментар":1,"можн":1,"повыс":1,"ниж":1,"форм":1,"увер":1,"будеш":1,"брат":1,"сэр":1,"so":1,"dass":1,"er":1,"мистер":1,"ж":1,"завязыва":1,"тренирова":1,"невежеств":1,"от":1,"парн":1,"них":1,"бол":1,"высок":1,"оценок":1,"о":1,"себ":1,"главн":1,"важн":1,"вам":1,"понрав":1,"такж":1,"злит":1,"расстро":1,"оценк":1,"встрет":1,"перевед":1,"озвуч":1,"специальн":1,"евр":1,"футбол":1,"подписыва":1,"жми":1,"колокольчик":1,"пропуска":1,"музык":1}]